restapi_library/__init__.py
restapi_library/cli.py
restapi_library/auth/__init__.py
restapi_library/auth/base.py
restapi_library/auth/dynamic_token.py
restapi_library/auth/factory.py
restapi_library/auth/handlers.py
restapi_library/cache/__init__.py
restapi_library/cache/base.py
restapi_library/cache/factory.py
restapi_library/cache/memory.py
restapi_library/cache/redis_cache.py
restapi_library/core/__init__.py
restapi_library/core/client.py
restapi_library/core/config.py
restapi_library/core/defaults.py
restapi_library/core/endpoint.py
restapi_library/core/exceptions.py
restapi_library/core/types.py
restapi_library/models/__init__.py
restapi_library/models/base.py
restapi_library/models/registry.py
restapi_library/models/response.py
restapi_library/utils/__init__.py
restapi_library/utils/decorators.py
restapi_library/utils/env_parser.py
restapi_library/utils/helpers.py
restapi_library/utils/logging.py
restapi_library/utils/retry.py
restapi_library/utils/validation.py
restapi_library-0.0.2.dist-info/licenses/LICENSE.txt
restapi_library-0.0.2.dist-info/METADATA
restapi_library-0.0.2.dist-info/WHEEL
restapi_library-0.0.2.dist-info/entry_points.txt
restapi_library-0.0.2.dist-info/top_level.txt
restapi_library-0.0.2.dist-info/RECORD
